pvrespeakerdemo/LICENSE
pvrespeakerdemo/__init__.py
pvrespeakerdemo/apa102.py
pvrespeakerdemo/picovoice_demo.py
pvrespeakerdemo/picovoice_raspberry-pi.ppn
pvrespeakerdemo/respeaker_raspberry-pi.rhn
pvrespeakerdemo-2.1.3.dist-info/METADATA
pvrespeakerdemo-2.1.3.dist-info/WHEEL
pvrespeakerdemo-2.1.3.dist-info/entry_points.txt
pvrespeakerdemo-2.1.3.dist-info/top_level.txt
pvrespeakerdemo-2.1.3.dist-info/RECORD
